deephaven/plugin/packaging/__init__.py
deephaven/plugin/packaging/utils.py
deephaven_plugin_packaging-0.0.1.dist-info/LICENSE
deephaven_plugin_packaging-0.0.1.dist-info/METADATA
deephaven_plugin_packaging-0.0.1.dist-info/WHEEL
deephaven_plugin_packaging-0.0.1.dist-info/top_level.txt
deephaven_plugin_packaging-0.0.1.dist-info/RECORD
