Metadata-Version: 2.1
Name: deephaven-plugin-packaging
Version: 0.0.1
Summary: Deephaven Plugin Packaging
Home-page: https://github.com/deephaven/deephaven-plugins
Author: Joe Numainville
Author-email: josephnumainville@deephaven.io
Project-URL: Source Code, https://github.com/deephaven/deephaven-plugins
Project-URL: Bug Tracker, https://github.com/deephaven/deephaven-plugins/issues
Keywords: deephaven,plugin,packaging
Platform: any
Classifier: Programming Language :: Python :: 3
Classifier: License :: OSI Approved :: Apache Software License
Classifier: Operating System :: OS Independent
Classifier: Environment :: Plugins
Classifier: Development Status :: 3 - Alpha
License-File: LICENSE
